collapse/__init__.py
collapse/symbolic/__init__.py
collapse/symbolic/constants.py
collapse/symbolic/coords.py
collapse/symbolic/curvature.py
collapse/symbolic/gravity.py
collapse/symbolic/matter.py
collapse/symbolic/metric.py
collapse/symbolic/symbols.py
collapse/symbolic/utilities.py
collapse/symbolic/tests/__init__.py
collapse/symbolic/tests/test_constants.py
collapse/symbolic/tests/test_coords.py
collapse/symbolic/tests/test_curvature.py
collapse/symbolic/tests/test_gravity.py
collapse/symbolic/tests/test_matter.py
collapse/symbolic/tests/test_metric.py
collapse/symbolic/tests/test_symbols.py
collapse/symbolic/tests/test_utilities.py
collapse/tests/__init__.py
collapse/tests/test_collapse.py
collapse-0.2.0.dist-info/LICENSE
collapse-0.2.0.dist-info/METADATA
collapse-0.2.0.dist-info/WHEEL
collapse-0.2.0.dist-info/top_level.txt
collapse-0.2.0.dist-info/RECORD
