Metadata-Version: 2.1
Name: collapse
Version: 0.2.0
Summary: Collapse
Home-page: https://github.com/JWKennington/collapse
Author: James Kennington
Author-email: jwkennington@psu.edu
License: MIT
Platform: UNKNOWN
Classifier: Programming Language :: Python
Classifier: Programming Language :: Python :: 3.7
Classifier: Programming Language :: Python :: 3.8
Classifier: Operating System :: MacOS
Classifier: Operating System :: POSIX :: Linux
Requires-Python: ==3.7, ==3.8
Requires-Dist: matplotlib
Requires-Dist: numpy
Requires-Dist: palettable
Requires-Dist: pytest
Requires-Dist: scipy
Requires-Dist: simpy
